odoo10_addon_l10n_fr_business_document_import-10.0.1.0.0-py2.7-nspkg.pth
odoo/addons/l10n_fr_business_document_import/README.rst
odoo/addons/l10n_fr_business_document_import/__init__.py
odoo/addons/l10n_fr_business_document_import/__manifest__.py
odoo/addons/l10n_fr_business_document_import/models/__init__.py
odoo/addons/l10n_fr_business_document_import/models/business_document_import.py
odoo/addons/l10n_fr_business_document_import/tests/__init__.py
odoo/addons/l10n_fr_business_document_import/tests/test_business_document_import.py
odoo10_addon_l10n_fr_business_document_import-10.0.1.0.0.dist-info/DESCRIPTION.rst
odoo10_addon_l10n_fr_business_document_import-10.0.1.0.0.dist-info/METADATA
odoo10_addon_l10n_fr_business_document_import-10.0.1.0.0.dist-info/RECORD
odoo10_addon_l10n_fr_business_document_import-10.0.1.0.0.dist-info/WHEEL
odoo10_addon_l10n_fr_business_document_import-10.0.1.0.0.dist-info/metadata.json
odoo10_addon_l10n_fr_business_document_import-10.0.1.0.0.dist-info/namespace_packages.txt
odoo10_addon_l10n_fr_business_document_import-10.0.1.0.0.dist-info/top_level.txt
